CHANGES.rst
MANIFEST.in
README.md
pyproject.toml
requirements-ci.txt
requirements.txt
setup.cfg
setup.py
maml/apps/__init__.py
maml/apps/rfxas/__init__.py
maml/apps/rfxas/_core.py
maml/apps/rfxas/_prediction.py
maml/apps/rfxas/experiment.csv
maml/apps/rfxas/data/Edge_vs_atomNo.csv
maml/apps/rfxas/data/cmotif_labels.json
maml/apps/rfxas/data/cmotif_predict_elements.json
maml/apps/rfxas/data/cnum_predict_elements.json
maml/apps/rfxas/tests/models/cmotif/RandomForest_Al_c_env_ex_CN_4.sav
maml/apps/rfxas/tests/models/cnum/RandomForest_Al_c_num.sav
maml_apps_rfxas.egg-info/PKG-INFO
maml_apps_rfxas.egg-info/SOURCES.txt
maml_apps_rfxas.egg-info/dependency_links.txt
maml_apps_rfxas.egg-info/namespace_packages.txt
maml_apps_rfxas.egg-info/requires.txt
maml_apps_rfxas.egg-info/top_level.txt