Metadata-Version: 1.2
Name: maml-apps-rfxas
Version: 2021.3.2
Summary: maml-apps-rfxas is a maml add-on to perform RF analysis of X-ray Absorption Spectra.
Home-page: http://maml.ai/
Author: Materials Virtual Lab
Author-email: ongsp@eng.ucsd.edu
Maintainer: Shyue Ping Ong
Maintainer-email: ongsp@eng.ucsd.edu
License: BSD
Keywords: materials,science,deep,learning
Platform: UNKNOWN
Classifier: Programming Language :: Python :: 3
Classifier: Programming Language :: Python :: 3.8
Classifier: Development Status :: 4 - Beta
Classifier: Intended Audience :: Science/Research
Classifier: License :: OSI Approved :: MIT License
Classifier: Operating System :: OS Independent
Classifier: Topic :: Scientific/Engineering :: Information Analysis
Classifier: Topic :: Scientific/Engineering :: Physics
Classifier: Topic :: Scientific/Engineering :: Chemistry
Classifier: Topic :: Software Development :: Libraries :: Python Modules
